tartube/__init__.py
tartube/classes.py
tartube/config.py
tartube/dialogue.py
tartube/downloads.py
tartube/ffmpeg_tartube.py
tartube/files.py
tartube/formats.py
tartube/info.py
tartube/mainapp.py
tartube/mainwin.py
tartube/media.py
tartube/options.py
tartube/process.py
tartube/refresh.py
tartube/tartube
tartube/tidy.py
tartube/ttutils.py
tartube/updates.py
tartube/wizwin.py
tartube/xdg_tartube.py
tartube/icons/dialogue/newbie_classic_icon.png
tartube/icons/dialogue/newbie_icon_64.png
tartube/icons/dialogue/ready_icon_64.png
tartube/icons/dialogue/setup_classic_icon.png
tartube/icons/dialogue/system_icon_64.png
tartube/icons/dialogue/system_icon_anglo_64.png
tartube/icons/dialogue/system_icon_eesti_64.png
tartube/icons/dialogue/system_icon_xmas_64.png
tartube/icons/dialogue/yt_icon_32.png
tartube/icons/dialogue/yt_remind_icon_en.png
tartube/icons/dialogue/yt_remind_icon_es.png
tartube/icons/dialogue/yt_remind_icon_fr.png
tartube/icons/dialogue/yt_remind_icon_kr.png
tartube/icons/dialogue/yt_remind_icon_nl.png
tartube/icons/dialogue/yt_remind_icon_ru.png
tartube/icons/dialogue/yt_remind_icon_vi.png
tartube/icons/external/youtube-dl-gui.png
tartube/icons/ico/tartube_icon.ico
tartube/icons/large/attention.png
tartube/icons/large/channel.png
tartube/icons/large/copy.png
tartube/icons/large/cursor.png
tartube/icons/large/error.png
tartube/icons/large/folder_black.png
tartube/icons/large/folder_blue.png
tartube/icons/large/folder_green.png
tartube/icons/large/folder_red.png
tartube/icons/large/folder_yellow.png
tartube/icons/large/hand_left.png
tartube/icons/large/hand_right.png
tartube/icons/large/learn_left.png
tartube/icons/large/learn_right.png
tartube/icons/large/limits_off.png
tartube/icons/large/limits_on.png
tartube/icons/large/playlist.png
tartube/icons/large/question.png
tartube/icons/large/video.png
tartube/icons/large/warning.png
tartube/icons/locale/Word_Tamil.svg.png
tartube/icons/locale/flag_de.png
tartube/icons/locale/flag_en_GB.png
tartube-2.5.197.dist-info/AUTHORS
tartube-2.5.197.dist-info/LICENSE
tartube-2.5.197.dist-info/METADATA
tartube-2.5.197.dist-info/WHEEL
tartube-2.5.197.dist-info/top_level.txt
tartube-2.5.197.dist-info/RECORD
