Metadata-Version: 2.1
Name: tartube
Version: 2.5.197
Summary: GUI front-end for youtube-dl and yt-dlp
Home-page: https://tartube.sourceforge.io
Author: A S Lewis
Author-email: aslewis@cpan.org
License: LGPLv2.1+
Project-URL: Bug Reports, https://github.com/axcore/tartube/issues
Project-URL: Source, https://github.com/axcore/tartube
Keywords: tartube video download youtube
Classifier: Development Status :: 5 - Production/Stable
Classifier: Intended Audience :: End Users/Desktop
Classifier: Topic :: Multimedia :: Video
Classifier: License :: OSI Approved :: GNU Lesser General Public License v2 or later (LGPLv2+)
Classifier: Programming Language :: Python :: 3
Classifier: Programming Language :: Python :: 3.4
Classifier: Programming Language :: Python :: 3.5
Classifier: Programming Language :: Python :: 3.6
Classifier: Programming Language :: Python :: 3.7
Classifier: Programming Language :: Python :: 3.8
Classifier: Programming Language :: Python :: 3.9
Classifier: Programming Language :: Python :: 3.10
Classifier: Programming Language :: Python :: 3.11
Classifier: Programming Language :: Python :: 3.12
Requires-Python: >=3.0, <4
License-File: LICENSE
License-File: AUTHORS
Requires-Dist: feedparser
Requires-Dist: pygobject
Requires-Dist: requests
